mspp_management/service_client_base.py
mspp_management/analytics/analytics_request_builder.py
mspp_management/analytics/actions/actions_request_builder.py
mspp_management/analytics/actions/item/with_action_name_item_request_builder.py
mspp_management/analytics/advisor_recommendations/advisor_recommendations_request_builder.py
mspp_management/analytics/advisor_recommendations/item/with_scenario_item_request_builder.py
mspp_management/analytics/advisor_recommendations/item/actionmetadata/actionmetadata_request_builder.py
mspp_management/analytics/advisor_recommendations/item/actionmetadata/item/with_action_name_get_response.py
mspp_management/analytics/advisor_recommendations/item/actionmetadata/item/with_action_name_item_request_builder.py
mspp_management/analytics/advisor_recommendations/item/actions/actions_request_builder.py
mspp_management/analytics/advisor_recommendations/item/resources/resources_request_builder.py
mspp_management/analytics/advisor_recommendations/scenarios/scenarios_request_builder.py
mspp_management/appmanagement/appmanagement_request_builder.py
mspp_management/appmanagement/application_packages/application_packages_request_builder.py
mspp_management/appmanagement/environments/environments_request_builder.py
mspp_management/appmanagement/environments/item/with_environment_item_request_builder.py
mspp_management/appmanagement/environments/item/application_packages/application_packages_request_builder.py
mspp_management/appmanagement/environments/item/application_packages/item/with_unique_name_item_request_builder.py
mspp_management/appmanagement/environments/item/application_packages/item/install/install_request_builder.py
mspp_management/appmanagement/environments/item/operations/operations_request_builder.py
mspp_management/appmanagement/environments/item/operations/item/with_operation_item_request_builder.py
mspp_management/authorization/authorization_request_builder.py
powerplatform_management-2.0.3232.199.dist-info/licenses/LICENSE.md
powerplatform_management-2.0.3232.199.dist-info/METADATA
powerplatform_management-2.0.3232.199.dist-info/WHEEL
powerplatform_management-2.0.3232.199.dist-info/top_level.txt
powerplatform_management-2.0.3232.199.dist-info/RECORD
