Metadata-Version: 2.4
Name: powerplatform-management
Version: 2.0.3232.199
Summary: Microsoft Power Platform Management SDK
Author: Microsoft Corporation
License-Expression: MIT
Project-URL: homepage, https://learn.microsoft.com/rest/api/power-platform/
Requires-Python: >=3.8
License-File: LICENSE.md
Requires-Dist: asyncio>=4.0.0
Requires-Dist: azure-identity-broker>=1.3.0
Requires-Dist: microsoft-kiota-authentication-azure>=1.9.6
Requires-Dist: microsoft-kiota-http>=1.9.6
Requires-Dist: microsoft-kiota-serialization-form>=1.9.6
Requires-Dist: microsoft-kiota-serialization-json>=1.9.6
Requires-Dist: microsoft-kiota-serialization-multipart>=1.9.6
Requires-Dist: microsoft-kiota-serialization-text>=1.9.6
Requires-Dist: msal-extensions>=1.3.1
Dynamic: license-file
